titan_package/__init__.py
titan_package/titan_package.py
titan_package/version.py
titan_package/lib/__init__.py
titan_package/lib/extended2.py
titan_package/lib/lib.py
titan_package/lib/satu.py
titan_package-0.0.2.dist-info/METADATA
titan_package-0.0.2.dist-info/WHEEL
titan_package-0.0.2.dist-info/top_level.txt
titan_package-0.0.2.dist-info/RECORD
