Metadata-Version: 2.1
Name: titan-package
Version: 0.0.2
Summary: A description of your package.
Author: titanabrian
Keywords: test,package
